[
  {
    "id": "mclaren",
    "name": "McLaren",
    "shortName": "MCL",
    "country": "Royaume-Uni",
    "founded": "années 1960",
    "drivers": ["Lando Norris", "Oscar Piastri"],
    "identity": "Écurie reconnue pour son approche technique, ses innovations et plusieurs générations de monoplaces marquantes.",
    "strengths": ["Châssis", "Innovation", "Culture ingénieur"],
    "notableCars": ["MP4/4", "MP4-23", "MCL38"],
    "colors": { "primary": "#ff8700", "secondary": "#111111", "accent": "#47c7fc" },
    "source": "formula1-teams-2026",
    "logoUrl": "https://media.formula1.com/image/upload/c_lfill,w_160/q_auto/v1740000001/common/f1/2026/mclaren/2026mclarenlogowhite.webp",
    "carImageUrl": "https://media.formula1.com/image/upload/c_lfill,w_512/q_auto/d_common:f1:2026:fallback:car:2026fallbackcarright.webp/v1740000001/common/f1/2026/mclaren/2026mclarencarright.webp"
  },
  {
    "id": "mercedes",
    "name": "Mercedes",
    "shortName": "MER",
    "country": "Allemagne / Royaume-Uni",
    "founded": "retour constructeur moderne en 2010",
    "drivers": ["George Russell", "Kimi Antonelli"],
    "identity": "Écurie devenue dominante pendant l'ère hybride grâce à l'intégration moteur, châssis et organisation.",
    "strengths": ["Hybridation", "Organisation", "Exploitation course"],
    "notableCars": ["W05", "W11", "W12"],
    "colors": { "primary": "#00a19c", "secondary": "#c8ccce", "accent": "#57f2d0" },
    "source": "formula1-teams-2026",
    "logoUrl": "https://media.formula1.com/image/upload/c_lfill,w_160/q_auto/v1740000001/common/f1/2026/mercedes/2026mercedeslogowhite.webp",
    "carImageUrl": "https://media.formula1.com/image/upload/c_lfill,w_512/q_auto/d_common:f1:2026:fallback:car:2026fallbackcarright.webp/v1740000001/common/f1/2026/mercedes/2026mercedescarright.webp"
  },
  {
    "id": "ferrari",
    "name": "Ferrari",
    "shortName": "FER",
    "country": "Italie",
    "founded": "1950 en championnat du monde",
    "drivers": ["Charles Leclerc", "Lewis Hamilton"],
    "identity": "Écurie historique associée aux voitures rouges, à la passion populaire et à une présence continue en F1.",
    "strengths": ["Héritage", "Moteur", "Culture de la compétition"],
    "notableCars": ["312T", "F2004", "SF-26"],
    "colors": { "primary": "#e10600", "secondary": "#1c1c1c", "accent": "#ffd22e" },
    "source": "formula1-teams-2026",
    "logoUrl": "https://media.formula1.com/image/upload/c_lfill,w_160/q_auto/v1740000001/common/f1/2026/ferrari/2026ferrarilogowhite.webp",
    "carImageUrl": "https://media.formula1.com/image/upload/c_lfill,w_512/q_auto/d_common:f1:2026:fallback:car:2026fallbackcarright.webp/v1740000001/common/f1/2026/ferrari/2026ferraricarright.webp"
  },
  {
    "id": "red-bull",
    "name": "Red Bull Racing",
    "shortName": "RBR",
    "country": "Autriche / Royaume-Uni",
    "founded": "2005",
    "drivers": ["Max Verstappen", "Isack Hadjar"],
    "identity": "Écurie moderne connue pour son aérodynamique, son identité sportive forte et sa capacité à exploiter les règlements.",
    "strengths": ["Aérodynamique", "Stratégie", "Développement"],
    "notableCars": ["RB7", "RB9", "RB19"],
    "colors": { "primary": "#1e41ff", "secondary": "#060b2d", "accent": "#fcd700" },
    "source": "formula1-teams-2026",
    "logoUrl": "https://media.formula1.com/image/upload/c_lfill,w_160/q_auto/v1740000001/common/f1/2026/redbullracing/2026redbullracinglogowhite.webp",
    "carImageUrl": "https://media.formula1.com/image/upload/c_lfill,w_512/q_auto/d_common:f1:2026:fallback:car:2026fallbackcarright.webp/v1740000001/common/f1/2026/redbullracing/2026redbullracingcarright.webp"
  },
  {
    "id": "williams",
    "name": "Williams",
    "shortName": "WIL",
    "country": "Royaume-Uni",
    "founded": "années 1970",
    "drivers": ["Carlos Sainz", "Alexander Albon"],
    "identity": "Écurie indépendante devenue une référence historique grâce à des voitures efficaces et une forte culture de course.",
    "strengths": ["Efficacité", "Histoire", "Formation de talents"],
    "notableCars": ["FW14B", "FW18", "FW19"],
    "colors": { "primary": "#005aff", "secondary": "#0a1020", "accent": "#8fd3ff" },
    "source": "formula1-teams-2026",
    "logoUrl": "https://media.formula1.com/image/upload/c_lfill,w_160/q_auto/v1740000001/common/f1/2026/williams/2026williamslogowhite.webp",
    "carImageUrl": "https://media.formula1.com/image/upload/c_lfill,w_512/q_auto/d_common:f1:2026:fallback:car:2026fallbackcarright.webp/v1740000001/common/f1/2026/williams/2026williamscarright.webp"
  },
  {
    "id": "aston-martin",
    "name": "Aston Martin",
    "shortName": "AMR",
    "country": "Royaume-Uni",
    "founded": "retour moderne sous ce nom en 2021",
    "drivers": ["Fernando Alonso", "Lance Stroll"],
    "identity": "Écurie construite autour d'une identité britannique premium, avec une forte ambition technique.",
    "strengths": ["Développement", "Infrastructure", "Expérience pilote"],
    "notableCars": ["AMR21", "AMR23", "AMR26"],
    "colors": { "primary": "#006f62", "secondary": "#0a2f2a", "accent": "#cedc00" },
    "source": "formula1-teams-2026",
    "logoUrl": "https://media.formula1.com/image/upload/c_lfill,w_160/q_auto/v1740000001/common/f1/2026/astonmartin/2026astonmartinlogowhite.webp",
    "carImageUrl": "https://media.formula1.com/image/upload/c_lfill,w_512/q_auto/d_common:f1:2026:fallback:car:2026fallbackcarright.webp/v1740000001/common/f1/2026/astonmartin/2026astonmartincarright.webp"
  },
  {
    "id": "racing-bulls",
    "name": "Racing Bulls",
    "shortName": "VCARB",
    "country": "Italie / Royaume-Uni",
    "founded": "structure issue de Minardi et Toro Rosso",
    "drivers": ["Liam Lawson", "Arvid Lindblad"],
    "identity": "Écurie sœur de Red Bull, souvent utilisée pour développer des talents et tester des orientations techniques.",
    "strengths": ["Formation", "Agilité", "Lien Red Bull"],
    "notableCars": ["STR14", "AT01", "VCARB 01"],
    "colors": { "primary": "#2b5cff", "secondary": "#f3f3f3", "accent": "#e10600" },
    "source": "formula1-teams-2026",
    "logoUrl": "https://media.formula1.com/image/upload/c_lfill,w_160/q_auto/v1740000001/common/f1/2026/racingbulls/2026racingbullslogowhite.webp",
    "carImageUrl": "https://media.formula1.com/image/upload/c_lfill,w_512/q_auto/d_common:f1:2026:fallback:car:2026fallbackcarright.webp/v1740000001/common/f1/2026/racingbulls/2026racingbullscarright.webp"
  },
  {
    "id": "haas",
    "name": "Haas F1 Team",
    "shortName": "Haas",
    "country": "États-Unis",
    "founded": "2016 en F1",
    "drivers": ["Esteban Ocon", "Oliver Bearman"],
    "identity": "Écurie américaine au modèle compact, axée sur l'efficacité opérationnelle et les partenariats techniques.",
    "strengths": ["Simplicité", "Réactivité", "Approche pragmatique"],
    "notableCars": ["VF-16", "VF-22", "VF-26"],
    "colors": { "primary": "#f5f5f5", "secondary": "#111111", "accent": "#e10600" },
    "source": "formula1-teams-2026",
    "logoUrl": "https://media.formula1.com/image/upload/c_lfill,w_160/q_auto/v1740000001/common/f1/2026/haasf1team/2026haasf1teamlogowhite.webp",
    "carImageUrl": "https://media.formula1.com/image/upload/c_lfill,w_512/q_auto/d_common:f1:2026:fallback:car:2026fallbackcarright.webp/v1740000001/common/f1/2026/haasf1team/2026haasf1teamcarright.webp"
  },
  {
    "id": "alpine",
    "name": "Alpine",
    "shortName": "ALP",
    "country": "France",
    "founded": "présence sous plusieurs identités Renault / Alpine",
    "drivers": ["Pierre Gasly", "Franco Colapinto"],
    "identity": "Projet français lié à l'histoire des moteurs turbo, aux titres constructeur et à une présence technique importante.",
    "strengths": ["Identité française", "Formation", "Culture moteur"],
    "notableCars": ["RS01", "R25", "A522"],
    "colors": { "primary": "#2293d1", "secondary": "#ff87bc", "accent": "#f5f5f5" },
    "source": "formula1-teams-2026",
    "logoUrl": "https://media.formula1.com/image/upload/c_lfill,w_160/q_auto/v1740000001/common/f1/2026/alpine/2026alpinelogowhite.webp",
    "carImageUrl": "https://media.formula1.com/image/upload/c_lfill,w_512/q_auto/d_common:f1:2026:fallback:car:2026fallbackcarright.webp/v1740000001/common/f1/2026/alpine/2026alpinecarright.webp"
  },
  {
    "id": "audi",
    "name": "Audi",
    "shortName": "AUD",
    "country": "Allemagne / Suisse",
    "founded": "arrivée comme équipe d'usine en 2026",
    "drivers": ["Nico Hülkenberg", "Gabriel Bortoleto"],
    "identity": "Nouvelle équipe d'usine issue de Sauber, centrée sur le règlement moteur 2026 et l'intégration constructeur.",
    "strengths": ["Projet constructeur", "Moteur", "Développement long terme"],
    "notableCars": ["C44", "R26"],
    "colors": { "primary": "#c7ff00", "secondary": "#111111", "accent": "#f5f5f5" },
    "source": "formula1-teams-2026",
    "logoUrl": "https://media.formula1.com/image/upload/c_lfill,w_160/q_auto/v1740000001/common/f1/2026/audi/2026audilogowhite.webp",
    "carImageUrl": "https://media.formula1.com/image/upload/c_lfill,w_512/q_auto/d_common:f1:2026:fallback:car:2026fallbackcarright.webp/v1740000001/common/f1/2026/audi/2026audicarright.webp"
  },
  {
    "id": "cadillac",
    "name": "Cadillac",
    "shortName": "CAD",
    "country": "États-Unis",
    "founded": "début en F1 en 2026",
    "drivers": ["Sergio Perez", "Valtteri Bottas"],
    "identity": "Nouvelle écurie américaine qui élargit la grille et apporte une identité constructeur forte.",
    "strengths": ["Nouveau projet", "Expérience pilotes", "Ambition constructeur"],
    "notableCars": ["MAC-26"],
    "colors": { "primary": "#111111", "secondary": "#d6b25e", "accent": "#e10600" },
    "source": "formula1-teams-2026",
    "logoUrl": "https://media.formula1.com/image/upload/c_lfill,w_160/q_auto/v1740000001/common/f1/2026/cadillac/2026cadillaclogowhite.webp",
    "carImageUrl": "https://media.formula1.com/image/upload/c_lfill,w_512/q_auto/d_common:f1:2026:fallback:car:2026fallbackcarright.webp/v1740000001/common/f1/2026/cadillac/2026cadillaccarright.webp"
  }
]
